nasse/.gitignore
nasse/LICENSE
nasse/__info__.py
nasse/__init__.py
nasse/__main__.py
nasse/config.py
nasse/docs/__init__.py
nasse/docs/curl.py
nasse/docs/example.py
nasse/docs/header.py
nasse/docs/javascript.py
nasse/docs/markdown.py
nasse/docs/postman.py
nasse/docs/python.py
nasse/exceptions/__init__.py
nasse/exceptions/arguments.py
nasse/exceptions/authentication.py
nasse/exceptions/base.py
nasse/exceptions/request.py
nasse/exceptions/validate.py
nasse/localization/__init__.py
nasse/localization/base.py
nasse/localization/eng.py
nasse/localization/fra.py
nasse/localization/jpn.py
nasse/logging.py
nasse/models.py
nasse/nasse.py
nasse/receive.py
nasse/request.py
nasse/requirements.txt
nasse/response.py
nasse/servers/__init__.py
nasse/servers/flask.py
nasse/servers/gunicorn.py
nasse/tui/README.md
nasse/tui/__init__.py
nasse/tui/app.py
nasse/tui/apps/__init__.py
nasse/tui/apps/http_app.py
nasse/tui/apps/runner_app.py
nasse/tui/components/__init__.py
nasse/tui/components/forms.py
nasse/tui/components/headers.py
nasse/tui/components/history.py
nasse/tui/components/inputs.py
nasse/tui/components/series.py
nasse/tui/components/texts.py
nasse/tui/screens/__init__.py
nasse/tui/screens/filebrowser.py
nasse/tui/screens/options.py
nasse/tui/screens/quit.py
nasse/tui/styles/http.css
nasse/tui/styles/runner.css
nasse/tui/widget.py
nasse/utils/__init__.py
nasse/utils/args.py
nasse/utils/boolean.py
nasse/utils/formatter.py
nasse/utils/ip.py
nasse/utils/json.py
nasse/utils/logging.py
nasse/utils/router.py
nasse/utils/sanitize.py
nasse/utils/static.py
nasse/utils/timer.py
nasse/utils/types.py
nasse/utils/unpack.py
nasse/utils/xml.py
nasse-2.0.2.dist-info/LICENSE
nasse-2.0.2.dist-info/METADATA
nasse-2.0.2.dist-info/WHEEL
nasse-2.0.2.dist-info/entry_points.txt
nasse-2.0.2.dist-info/RECORD
