Metadata-Version: 2.1
Name: nasse
Version: 2.0.2
Summary: A web server framework written on top of Flask which lets you focus on your ideas 🍡
Home-page: https://github.com/Animenosekai/nasse
License: MIT
Keywords: animenosekai,nasse,flask,framework,web,web-server,web-framework,docs,documentation,http,requests
Author: Animenosekai
Author-email: animenosekai.mail@gmail.com
Maintainer: Animenosekai
Maintainer-email: animenosekai.mail@gmail.com
Requires-Python: >=3.8,<4.0
Classifier: Development Status :: 5 - Production/Stable
Classifier: Environment :: Console
Classifier: Environment :: Web Environment
Classifier: Framework :: Flask
Classifier: Intended Audience :: Developers
Classifier: License :: OSI Approved :: MIT License
Classifier: Operating System :: OS Independent
Classifier: Programming Language :: Python
Classifier: Programming Language :: Python :: 3
Classifier: Programming Language :: Python :: 3.8
Classifier: Programming Language :: Python :: 3.9
Classifier: Programming Language :: Python :: 3.10
Classifier: Programming Language :: Python :: 3.11
Classifier: Topic :: Documentation
Classifier: Topic :: Internet
Classifier: Topic :: Internet :: WWW/HTTP :: Dynamic Content
Classifier: Topic :: Internet :: WWW/HTTP :: HTTP Servers
Classifier: Topic :: Internet :: WWW/HTTP :: WSGI
Classifier: Topic :: Software Development :: Libraries :: Application Frameworks
Classifier: Typing :: Typed
Requires-Dist: flask (>=2,<3)
Requires-Dist: flask-compress (>=1.10,<2.0)
Requires-Dist: miko (>=1.1,<2.0)
Requires-Dist: nh3 (>=0.2.14,<0.3.0)
Requires-Dist: requests (>=2,<3)
Requires-Dist: rich (>=13,<14)
Requires-Dist: textual (>=0.30.0,<0.31.0)
Requires-Dist: watchdog (>=3.0.0,<4.0.0)
Project-URL: Documentation, https://github.com/Animenosekai/nasse/blob/main/README.md
Project-URL: Issue Tracker, https://github.com/Animenosekai/nasse/issues
Project-URL: Repository, https://github.com/Animenosekai/nasse
